investments/__init__.py
investments/investments.py
my_investments-0.1.dist-info/licenses/LICENSE
my_investments-0.1.dist-info/METADATA
my_investments-0.1.dist-info/WHEEL
my_investments-0.1.dist-info/top_level.txt
my_investments-0.1.dist-info/RECORD
