Metadata-Version: 2.4
Name: my_investments
Version: 0.1
Summary: Uma biblioteca para cálculos de investimentos criada no curso IA para devs da FIAP em 2025.
Home-page: https://github.com/RobertoCosta33/my_investments
Author: Roberto Barbosa Costa
Author-email: rbt.desenvolvimentos@gmail.com
Classifier: Programming Language :: Python :: 3
Classifier: License :: OSI Approved :: MIT License
Classifier: Operating System :: OS Independent
Requires-Python: >=3.6
License-File: LICENSE
Dynamic: author
Dynamic: author-email
Dynamic: classifier
Dynamic: home-page
Dynamic: license-file
Dynamic: requires-python
Dynamic: summary
